autosyspath/__init__.py
toautosyspath-0.0.1.dist-info/LICENSE
toautosyspath-0.0.1.dist-info/METADATA
toautosyspath-0.0.1.dist-info/WHEEL
toautosyspath-0.0.1.dist-info/top_level.txt
toautosyspath-0.0.1.dist-info/zip-safe
toautosyspath-0.0.1.dist-info/RECORD
