Metadata-Version: 2.1
Name: toautosyspath
Version: 0.0.1
Summary: A python automatically adds the current project sys Path tool
Home-page: https://github.com/dragons96/autosyspath
Author: dragons
Author-email: 521274311@qq.com
Classifier: Intended Audience :: Developers
Classifier: Programming Language :: Python :: 3.7
Classifier: Topic :: Software Development :: Libraries
License-File: LICENSE
